{"artifactVersion":"1.1.15","description":"Is this value a JS Typed Array? This module works cross-realm/iframe, does not depend on `instanceof` or mutable properties, and despite ES6 Symbol.toStringTag.","developers":[{"name":"Jordan Harband","organisationUrl":""}],"licenses":["MIT_09645df36c2b7bc1360fdc1f353c2b382c612ec754ee86ed413738a68106b75b9393ddcc108d905b4d6c5c82deb6a311828629e0420a41934734242b00b3858f"],"name":"is-typed-array","tag":"","uniqueId":"is-typed-array@1.1.15","website":"https://github.com/inspect-js/is-typed-array"}